odoo10_addon_stock_quant_reserved_qty_uom-10.0.1.0.0-py2.7-nspkg.pth
odoo/addons/stock_quant_reserved_qty_uom/README.rst
odoo/addons/stock_quant_reserved_qty_uom/__init__.py
odoo/addons/stock_quant_reserved_qty_uom/__manifest__.py
odoo/addons/stock_quant_reserved_qty_uom/models/__init__.py
odoo/addons/stock_quant_reserved_qty_uom/models/stock_quant.py
odoo/addons/stock_quant_reserved_qty_uom/static/description/icon.png
odoo/addons/stock_quant_reserved_qty_uom/tests/__init__.py
odoo/addons/stock_quant_reserved_qty_uom/tests/test_stock_quant_reserved_qty_uom.py
odoo/addons/stock_quant_reserved_qty_uom/views/stock_quant_view.xml
odoo10_addon_stock_quant_reserved_qty_uom-10.0.1.0.0.dist-info/DESCRIPTION.rst
odoo10_addon_stock_quant_reserved_qty_uom-10.0.1.0.0.dist-info/METADATA
odoo10_addon_stock_quant_reserved_qty_uom-10.0.1.0.0.dist-info/RECORD
odoo10_addon_stock_quant_reserved_qty_uom-10.0.1.0.0.dist-info/WHEEL
odoo10_addon_stock_quant_reserved_qty_uom-10.0.1.0.0.dist-info/metadata.json
odoo10_addon_stock_quant_reserved_qty_uom-10.0.1.0.0.dist-info/namespace_packages.txt
odoo10_addon_stock_quant_reserved_qty_uom-10.0.1.0.0.dist-info/top_level.txt
